main.py
mseep_mcp_server_mas_sequential_thinking-0.4.1.dist-info/METADATA
mseep_mcp_server_mas_sequential_thinking-0.4.1.dist-info/WHEEL
mseep_mcp_server_mas_sequential_thinking-0.4.1.dist-info/entry_points.txt
mseep_mcp_server_mas_sequential_thinking-0.4.1.dist-info/RECORD
